{
    "total": [
        {
            "id": "61559235542444",
            "count": 0
        },
        {
            "id": "100038740121428",
            "count": 47
        },
        {
            "id": "61559777633272",
            "count": 0
        },
        {
            "id": "61559996030885",
            "count": 0
        },
        {
            "id": "61560049491747",
            "count": 0
        },
        {
            "id": "61559530484938",
            "count": 0
        },
        {
            "id": "61560099980547",
            "count": 0
        },
        {
            "id": "61560404631644",
            "count": 0
        },
        {
            "id": "61560118331700",
            "count": 0
        },
        {
            "id": "61558510602126",
            "count": 0
        },
        {
            "id": "61560069467799",
            "count": 0
        },
        {
            "id": "61559438575046",
            "count": 0
        },
        {
            "id": "61560654511584",
            "count": 0
        },
        {
            "id": "61560926830133",
            "count": 0
        },
        {
            "id": "61559282801359",
            "count": 0
        },
        {
            "id": "61560606513186",
            "count": 0
        },
        {
            "id": "100083847474323",
            "count": 0
        },
        {
            "id": "61553763794708",
            "count": 0
        },
        {
            "id": "61552084853331",
            "count": 0
        },
        {
            "id": "61561570561761",
            "count": 0
        },
        {
            "id": "100075784943859",
            "count": 61
        },
        {
            "id": "61561504335762",
            "count": 0
        },
        {
            "id": "61559903816343",
            "count": 0
        },
        {
            "id": "61560450915670",
            "count": 0
        },
        {
            "id": "61556755597888",
            "count": 0
        },
        {
            "id": "61561947542709",
            "count": 0
        },
        {
            "id": "100088031225325",
            "count": 155
        },
        {
            "id": "61557790880926",
            "count": 0
        },
        {
            "id": "61562151205816",
            "count": 0
        },
        {
            "id": "61550022652935",
            "count": 0
        },
        {
            "id": "61561608374000",
            "count": 1
        },
        {
            "id": "61561727491080",
            "count": 0
        },
        {
            "id": "61561995988657",
            "count": 0
        },
        {
            "id": "100078717550219",
            "count": 0
        },
        {
            "id": "61561985909917",
            "count": 0
        },
        {
            "id": "61562071387946",
            "count": 0
        },
        {
            "id": "61560368315094",
            "count": 0
        },
        {
            "id": "100037780020873",
            "count": 0
        },
        {
            "id": "61562086451955",
            "count": 0
        },
        {
            "id": "61562040629561",
            "count": 2
        },
        {
            "id": "61562439355061",
            "count": 0
        },
        {
            "id": "100003927301105",
            "count": 0
        },
        {
            "id": "61562021202350",
            "count": 0
        },
        {
            "id": "61562211158190",
            "count": 0
        },
        {
            "id": "61562500093691",
            "count": 0
        },
        {
            "id": "100091435911117",
            "count": 0
        },
        {
            "id": "61562926262183",
            "count": 0
        },
        {
            "id": "61560407583530",
            "count": 0
        },
        {
            "id": "61561171259534",
            "count": 0
        },
        {
            "id": "61562206563697",
            "count": 0
        },
        {
            "id": "61563454850537",
            "count": 0
        },
        {
            "id": "61562249834774",
            "count": 0
        },
        {
            "id": "61550536127381",
            "count": 0
        },
        {
            "id": "100089459823872",
            "count": 0
        },
        {
            "id": "61555016023007",
            "count": 16
        },
        {
            "id": "100093795935793",
            "count": 0
        },
        {
            "id": "61562760102482",
            "count": 0
        },
        {
            "id": "61561601624319",
            "count": 0
        },
        {
            "id": "61562261835048",
            "count": 0
        },
        {
            "id": "61562746665106",
            "count": 7
        },
        {
            "id": "61563383187616",
            "count": 0
        },
        {
            "id": "61563382857673",
            "count": 0
        },
        {
            "id": "61561135898716",
            "count": 0
        },
        {
            "id": "61562787787460",
            "count": 0
        },
        {
            "id": "61560539282493",
            "count": 0
        },
        {
            "id": "61557591564921",
            "count": 0
        },
        {
            "id": "61554385056081",
            "count": 0
        },
        {
            "id": "61563088362521",
            "count": 0
        },
        {
            "id": "100001336014475",
            "count": 0
        },
        {
            "id": "100008362837847",
            "count": 0
        },
        {
            "id": "61563758873217",
            "count": 0
        },
        {
            "id": "61559772573500",
            "count": 0
        },
        {
            "id": "61563177670147",
            "count": 0
        },
        {
            "id": "61553829171376",
            "count": 0
        },
        {
            "id": "100093051642489",
            "count": 551
        },
        {
            "id": "61562716052902",
            "count": 3
        },
        {
            "id": "61561269682645",
            "count": 0
        },
        {
            "id": "61561331982821",
            "count": 0
        },
        {
            "id": "100093167650888",
            "count": 0
        },
        {
            "id": "61564054794604",
            "count": 0
        },
        {
            "id": "100001582801337",
            "count": 0
        },
        {
            "id": "61563812093380",
            "count": 0
        },
        {
            "id": "100031213101487",
            "count": 0
        },
        {
            "id": "61563455652121",
            "count": 0
        },
        {
            "id": "61560877683960",
            "count": 12
        },
        {
            "id": "61551718118258",
            "count": 0
        },
        {
            "id": "61560966655691",
            "count": 0
        },
        {
            "id": "61563517658089",
            "count": 0
        },
        {
            "id": "100020460654779",
            "count": 671
        },
        {
            "id": "61561697074493",
            "count": 0
        },
        {
            "id": "100091952226005",
            "count": 2
        },
        {
            "id": "61563269338729",
            "count": 0
        },
        {
            "id": "61562955388765",
            "count": 0
        },
        {
            "id": "61561401174728",
            "count": 0
        },
        {
            "id": "61563783135643",
            "count": 0
        },
        {
            "id": "100078831447837",
            "count": 12
        },
        {
            "id": "61562161232125",
            "count": 27
        },
        {
            "id": "100000576472277",
            "count": 0
        },
        {
            "id": "61561828030943",
            "count": 16
        },
        {
            "id": "61563212651510",
            "count": 0
        },
        {
            "id": "61564015621485",
            "count": 0
        },
        {
            "id": "61563763089474",
            "count": 0
        },
        {
            "id": "100095207345933",
            "count": 0
        },
        {
            "id": "100000364500247",
            "count": 0
        },
        {
            "id": "61555924809893",
            "count": 0
        },
        {
            "id": "61564602716515",
            "count": 44
        },
        {
            "id": "61563820294117",
            "count": 0
        },
        {
            "id": "61563981387983",
            "count": 0
        },
        {
            "id": "100001138147083",
            "count": 0
        },
        {
            "id": "61563957028755",
            "count": 219
        },
        {
            "id": "61563479344672",
            "count": 189
        },
        {
            "id": "61564347531917",
            "count": 21
        },
        {
            "id": "61563015765425",
            "count": 0
        },
        {
            "id": "61563588044195",
            "count": 115
        },
        {
            "id": "61562946966445",
            "count": 44
        },
        {
            "id": "61561642858727",
            "count": 0
        },
        {
            "id": "61565176111062",
            "count": 19
        },
        {
            "id": "100030236827904",
            "count": 0
        },
        {
            "id": "61564010925170",
            "count": 10
        },
        {
            "id": "61565118609699",
            "count": 37
        },
        {
            "id": "61564880897252",
            "count": 12
        },
        {
            "id": "61565496582725",
            "count": 37
        },
        {
            "id": "61553761838963",
            "count": 65
        },
        {
            "id": "100022267537746",
            "count": 0
        },
        {
            "id": "61566143271001",
            "count": 1
        },
        {
            "id": "100086225603286",
            "count": 1
        },
        {
            "id": "61561175279119",
            "count": 0
        }
    ],
    "week": [
        {
            "id": "61559235542444",
            "count": 0,
            "name": "ᏮᏮ ᏮᏮ"
        },
        {
            "id": "100038740121428",
            "count": 0,
            "name": "Duy メ"
        },
        {
            "id": "61559777633272",
            "count": 0,
            "name": "ᏮᏮᏮ ᏮᏮ"
        },
        {
            "id": "61559996030885",
            "count": 0,
            "name": "Người dùng Facebook"
        },
        {
            "id": "61560049491747",
            "count": 0,
            "name": "Người dùng Facebook"
        },
        {
            "id": "61559530484938",
            "count": 0,
            "name": "Người dùng Facebook"
        },
        {
            "id": "61560099980547",
            "count": 0,
            "name": "Người dùng Facebook"
        },
        {
            "id": "61560404631644",
            "count": 0,
            "name": "Người dùng Facebook"
        },
        {
            "id": "61560118331700",
            "count": 0,
            "name": "Người dùng Facebook"
        },
        {
            "id": "61558510602126",
            "count": 0,
            "name": "Người dùng Facebook"
        },
        {
            "id": "61560069467799",
            "count": 0,
            "name": "Người dùng Facebook"
        },
        {
            "id": "61559438575046",
            "count": 0,
            "name": "Ngg Văn Hiếu"
        },
        {
            "id": "61560654511584",
            "count": 0,
            "name": "Người dùng Facebook"
        },
        {
            "id": "61560926830133",
            "count": 0,
            "name": "Chỉ　Cần　Một　Ngày　Tồi　Tệ　 Thôi　Nó　Sẽ　Biến　Một　Kẻ　 Tỉnh　Táo　Thành　Một　Kẻ Điên"
        },
        {
            "id": "61559282801359",
            "count": 0,
            "name": "Hphong　Yeu　Chip　Ở Mọi　Vũ　Trụ"
        },
        {
            "id": "61560606513186",
            "count": 0,
            "name": "Người dùng Facebook"
        },
        {
            "id": "100083847474323",
            "count": 0,
            "name": "Nguyễn Quốc Pháp"
        },
        {
            "id": "61553763794708",
            "count": 0,
            "name": "Ng Hongg Ánhh"
        },
        {
            "id": "61552084853331",
            "count": 0,
            "name": "Người dùng Facebook"
        },
        {
            "id": "61561570561761",
            "count": 0,
            "name": "Người dùng Facebook"
        },
        {
            "id": "100075784943859",
            "count": 0,
            "name": "An Huỳnh"
        },
        {
            "id": "61561504335762",
            "count": 0,
            "name": "Người dùng Facebook"
        },
        {
            "id": "61559903816343",
            "count": 0,
            "name": "Người dùng Facebook"
        },
        {
            "id": "61560450915670",
            "count": 0,
            "name": "Người dùng Facebook"
        },
        {
            "id": "61556755597888",
            "count": 0,
            "name": "Nguyễn Văn Toàn"
        },
        {
            "id": "61561947542709",
            "count": 0,
            "name": "Người dùng Facebook"
        },
        {
            "id": "100088031225325",
            "count": 0,
            "name": "Lê Văn Hoàng"
        },
        {
            "id": "61557790880926",
            "count": 0,
            "name": "Người dùng Facebook"
        },
        {
            "id": "61562151205816",
            "count": 0,
            "name": "Người dùng Facebook"
        },
        {
            "id": "61550022652935",
            "count": 0,
            "name": "Kaiotard Chuche"
        },
        {
            "id": "61561608374000",
            "count": 0,
            "name": "Uyên Hạ"
        },
        {
            "id": "61561727491080",
            "count": 0,
            "name": "Người dùng Facebook"
        },
        {
            "id": "61561995988657",
            "count": 0,
            "name": "Người dùng Facebook"
        },
        {
            "id": "100078717550219",
            "count": 0,
            "name": "Trương Trần Mie"
        },
        {
            "id": "61561985909917",
            "count": 0,
            "name": "Người dùng Facebook"
        },
        {
            "id": "61562071387946",
            "count": 0,
            "name": "Người dùng Facebook"
        },
        {
            "id": "61560368315094",
            "count": 0,
            "name": "Người dùng Facebook"
        },
        {
            "id": "100037780020873",
            "count": 0,
            "name": "Người dùng Facebook"
        },
        {
            "id": "61562086451955",
            "count": 0,
            "name": "Người dùng Facebook"
        },
        {
            "id": "61562040629561",
            "count": 0,
            "name": "Nhi Bao"
        },
        {
            "id": "61562439355061",
            "count": 0,
            "name": "️️️️️️️️️️️️️️️️️️️️️️️️️️️️️️️️️️️️️️️️️️️️️️️️️️️️️️️️️️️️️️️️️️️️️️️️️️️️️️️️️️️️️️️️️️️️️️️️️️️️️️️️️️️️️️️️️️️️️️️️️️️️️️️️️️️️️️️️️️️️️️️️️️️️️️️️️️️️️️️️️️️️️️️️️️"
        },
        {
            "id": "100003927301105",
            "count": 0,
            "name": "Người dùng Facebook"
        },
        {
            "id": "61562021202350",
            "count": 0,
            "name": "Người dùng Facebook"
        },
        {
            "id": "61562211158190",
            "count": 0,
            "name": "Người dùng Facebook"
        },
        {
            "id": "61562500093691",
            "count": 0,
            "name": "Người dùng Facebook"
        },
        {
            "id": "100091435911117",
            "count": 0,
            "name": "Ph The Hoanq"
        },
        {
            "id": "61562926262183",
            "count": 0,
            "name": "Người dùng Facebook"
        },
        {
            "id": "61560407583530",
            "count": 0,
            "name": "Người dùng Facebook"
        },
        {
            "id": "61561171259534",
            "count": 0,
            "name": "Người dùng Facebook"
        },
        {
            "id": "61562206563697",
            "count": 0,
            "name": "ᏎᏎᏎ ᏎᏎᏎ"
        },
        {
            "id": "61563454850537",
            "count": 0,
            "name": "Người dùng Facebook"
        },
        {
            "id": "61562249834774",
            "count": 0,
            "name": "Người dùng Facebook"
        },
        {
            "id": "61550536127381",
            "count": 0,
            "name": "Người dùng Facebook"
        },
        {
            "id": "100089459823872",
            "count": 0,
            "name": "Liễu Như Yên"
        },
        {
            "id": "61555016023007",
            "count": 0,
            "name": "Ngg Văn Hiếu"
        },
        {
            "id": "100093795935793",
            "count": 0,
            "name": "Người dùng Facebook"
        },
        {
            "id": "61562760102482",
            "count": 0,
            "name": "Người dùng Facebook"
        },
        {
            "id": "61561601624319",
            "count": 0,
            "name": "Người dùng Facebook"
        },
        {
            "id": "61562261835048",
            "count": 0,
            "name": "Người dùng Facebook"
        },
        {
            "id": "61562746665106",
            "count": 0,
            "name": "Người dùng Facebook"
        },
        {
            "id": "61563383187616",
            "count": 0,
            "name": "Người dùng Facebook"
        },
        {
            "id": "61563382857673",
            "count": 0,
            "name": "Người dùng Facebook"
        },
        {
            "id": "61561135898716",
            "count": 0,
            "name": "Ngồitrongtoilet Gàohéttenem"
        },
        {
            "id": "61562787787460",
            "count": 0,
            "name": "Người dùng Facebook"
        },
        {
            "id": "61560539282493",
            "count": 0,
            "name": "Người dùng Facebook"
        },
        {
            "id": "61557591564921",
            "count": 0,
            "name": "Người dùng Facebook"
        },
        {
            "id": "61554385056081",
            "count": 0,
            "name": "Người dùng Facebook"
        },
        {
            "id": "61563088362521",
            "count": 0,
            "name": "Người dùng Facebook"
        },
        {
            "id": "100001336014475",
            "count": 0,
            "name": "Người dùng Facebook"
        },
        {
            "id": "100008362837847",
            "count": 0,
            "name": "Tomi Guru"
        },
        {
            "id": "61563758873217",
            "count": 0,
            "name": "Người dùng Facebook"
        },
        {
            "id": "61559772573500",
            "count": 0,
            "name": "Người dùng Facebook"
        },
        {
            "id": "61563177670147",
            "count": 0,
            "name": "Diệp An"
        },
        {
            "id": "61553829171376",
            "count": 0,
            "name": "Người dùng Facebook"
        },
        {
            "id": "100093051642489",
            "count": 0,
            "name": "Đỗ Hải Phong"
        },
        {
            "id": "61562716052902",
            "count": 0,
            "name": "O.o T.T O.o T.T O.o T.T O.o T.T O.o T.T O.o T.T O.o T.T O.o T.T O.o T.T O.o T.T O.o T.T O.o T.T O.o T.T O.o T.T O.o T.T O.o T.T O.o T.T O.o T.T O.o T.T O.o T.T O.o T.T O.o T.T O.o T.T O.o T.T O.o T.T O.o T.T O.o T.T O.o T.T O.o T.T O.o T.T O.o T.T O.o T.T O.o T.T O.o T.T O.o T.T O.o T.T O.o T.T O.o T.T O.o T.T O.o T.T O.o T.T O.o T.T O.o T.T O.o T.T O.o T.T O.o T.T O.o T.T"
        },
        {
            "id": "61561269682645",
            "count": 0,
            "name": "Người dùng Facebook"
        },
        {
            "id": "61561331982821",
            "count": 0,
            "name": "Người dùng Facebook"
        },
        {
            "id": "100093167650888",
            "count": 0,
            "name": "𓂄𓆩𑁍𓆪𓂁 Luật Giang Hồ Anh Chơi Bằng Sub 𓃙 Dame Bay Acc Những Thằng Trap Yêu Em 𓃺 Yêu Nhau Hai Chữ Địt Nhau 𓆤 Chia Tay Bỗn Chữ Phiên Đã Hết Hạn 𓆤 Lỡ Một Ngày Em Theo Thằng Khác Anh Đau Lòng Nhưng Không Khóc Đâu Em 𓅢 Miệng Mỉm Cười Nói Em Câu Cuối Thôi Đừng Buồn Lập Nick Mới Đi Em 𓅂 𝑵𝒈𝒖𝒚𝒆𝒏 𝑻𝒓𝒂𝒏 𝑳𝒐𝒏𝒈 𝑱𝑾 𓆥 Bất Tử Theo Thời Gian𓂄𓆩𑁍𓆪𓂁"
        },
        {
            "id": "61564054794604",
            "count": 0,
            "name": "Người dùng Facebook"
        },
        {
            "id": "100001582801337",
            "count": 0,
            "name": "Người dùng Facebook"
        },
        {
            "id": "61563812093380",
            "count": 0,
            "name": "Phan Ky"
        },
        {
            "id": "100031213101487",
            "count": 0,
            "name": "Người dùng Facebook"
        },
        {
            "id": "61563455652121",
            "count": 0,
            "name": "Người dùng Facebook"
        },
        {
            "id": "61560877683960",
            "count": 0,
            "name": "Nguyễn Nhi"
        },
        {
            "id": "61551718118258",
            "count": 0,
            "name": "Nguyễn Quốc Duy"
        },
        {
            "id": "61560966655691",
            "count": 0,
            "name": "Người dùng Facebook"
        },
        {
            "id": "61563517658089",
            "count": 0,
            "name": "Bé là bot của admin KyPhan"
        },
        {
            "id": "100020460654779",
            "count": 0,
            "name": "Ky Phan"
        },
        {
            "id": "61561697074493",
            "count": 0,
            "name": "Người dùng Facebook"
        },
        {
            "id": "100091952226005",
            "count": 0,
            "name": "Na Na"
        },
        {
            "id": "61563269338729",
            "count": 0,
            "name": "Người dùng Facebook"
        },
        {
            "id": "61562955388765",
            "count": 0,
            "name": "Người dùng Facebook"
        },
        {
            "id": "61561401174728",
            "count": 0,
            "name": "Người dùng Facebook"
        },
        {
            "id": "61563783135643",
            "count": 0,
            "name": "Người dùng Facebook"
        },
        {
            "id": "100078831447837",
            "count": 0,
            "name": "Quốc Pháp"
        },
        {
            "id": "61562161232125",
            "count": 0,
            "name": "Er Golden"
        },
        {
            "id": "100000576472277",
            "count": 0,
            "name": "Người dùng Facebook"
        },
        {
            "id": "61561828030943",
            "count": 0,
            "name": "Chu Hoàng Thanh Vũ"
        },
        {
            "id": "61563212651510",
            "count": 0,
            "name": "Linda Melina"
        },
        {
            "id": "61564015621485",
            "count": 0,
            "name": "Người dùng Facebook"
        },
        {
            "id": "61563763089474",
            "count": 0,
            "name": "Người dùng Facebook"
        },
        {
            "id": "100095207345933",
            "count": 0,
            "name": "Người dùng Facebook"
        },
        {
            "id": "100000364500247",
            "count": 0,
            "name": "Người dùng Facebook"
        },
        {
            "id": "61555924809893",
            "count": 0,
            "name": "ʬʬHacker Cuteeʬʬ KHI　ANH　BUON　ANH　THUONG　LUOT　FAYBUC　NHUNG　LUC　ANH　RANH　ANH　HOC　CACH　BAN　QUI　PHAI　MOT　NGAY　DEP　TROI　TRAI　TIM　EM　BI　KHOA　ANH　UNL　ROI　NHUNG　DAP　BAY　HAI　BA　LOVE　LOVE　LOVE　LOVE　LOVE　LOVE　HACKE　BAT　TU　YEWEM　O　MOI　VUX　TRU　QUAN　MAY　CHEM　CHI　MUON　YEU　MINH　EM　THOI　I　LOOVEE　YOUU　CHIUCHIU　YEUEMMOIVUTRU　TRUM　FIFAI　YEU　EM　KHONG　PHAI - VIII"
        },
        {
            "id": "61564602716515",
            "count": 0,
            "name": "Người dùng Facebook"
        },
        {
            "id": "61563820294117",
            "count": 0,
            "name": "Người dùng Facebook"
        },
        {
            "id": "61563981387983",
            "count": 0,
            "name": "Người dùng Facebook"
        },
        {
            "id": "100001138147083",
            "count": 0,
            "name": "Người dùng Facebook"
        },
        {
            "id": "61563957028755",
            "count": 0,
            "name": "Người dùng Facebook"
        },
        {
            "id": "61563479344672",
            "count": 0,
            "name": "Người dùng Facebook"
        },
        {
            "id": "61564347531917",
            "count": 0,
            "name": "Người dùng Facebook"
        },
        {
            "id": "61563015765425",
            "count": 0,
            "name": "Này Con"
        },
        {
            "id": "61563588044195",
            "count": 0,
            "name": "Người dùng Facebook"
        },
        {
            "id": "61562946966445",
            "count": 0,
            "name": "Người dùng Facebook"
        },
        {
            "id": "61561642858727",
            "count": 0,
            "name": "Người dùng Facebook"
        },
        {
            "id": "61565176111062",
            "count": 0,
            "name": "An Huỳnh"
        },
        {
            "id": "100030236827904",
            "count": 0,
            "name": "Nguyen Hao YT"
        },
        {
            "id": "61564010925170",
            "count": 0,
            "name": "Người dùng Facebook"
        },
        {
            "id": "61565118609699",
            "count": 0,
            "name": "Người dùng Facebook"
        },
        {
            "id": "61564880897252",
            "count": 0,
            "name": "Người dùng Facebook"
        },
        {
            "id": "61565496582725",
            "count": 0,
            "name": "ʬʬHphong Dzʬʬ ANK　LA　HOT　WAR　QUIQUAI　KE　NAM　TRUM　NEN　TANG　GAME　QUIQUAI　VA　ANK　LA　MOT　HOT　TRICKER　TAI　SEVER　VIET　NAM　NAY　LU　ĐU　MOI　NHU　ĐU　TRICK　ĐOI　BEM　CHA　THI　LE　CAI　TAY　LEN　MA　DAME　CAI　WALL　ANK　BAT　TU　VI　ANK　CO　THE　RENAME　MOI　LOAI　TEN　MA　NGUOI　THUONG　KHONG　THE　ĐAT　DUOC　NGAY　ANK　CON　TREN　CAI　MXH　NAY　THI　ANK　TU　TIN　UNLOCK　ALL　MOI　LOAI　KHOA　FAYBUT - X"
        },
        {
            "id": "61553761838963",
            "count": 0,
            "name": "Lê Bảo"
        },
        {
            "id": "100022267537746",
            "count": 0,
            "name": "An Nguyen Ngoc"
        },
        {
            "id": "61566143271001",
            "count": 0,
            "name": "Người dùng Facebook"
        },
        {
            "id": "100086225603286",
            "count": 0,
            "name": "Ky Phan"
        },
        {
            "id": "61561175279119",
            "count": 0,
            "name": "Chữ Hờ Biết Nói"
        }
    ],
    "day": [
        {
            "id": "61559235542444",
            "count": 0,
            "name": "ᏮᏮ ᏮᏮ"
        },
        {
            "id": "100038740121428",
            "count": 0,
            "name": "Duy メ"
        },
        {
            "id": "61559777633272",
            "count": 0,
            "name": "ᏮᏮᏮ ᏮᏮ"
        },
        {
            "id": "61559996030885",
            "count": 0,
            "name": "Người dùng Facebook"
        },
        {
            "id": "61560049491747",
            "count": 0,
            "name": "Người dùng Facebook"
        },
        {
            "id": "61559530484938",
            "count": 0,
            "name": "Người dùng Facebook"
        },
        {
            "id": "61560099980547",
            "count": 0,
            "name": "Người dùng Facebook"
        },
        {
            "id": "61560404631644",
            "count": 0,
            "name": "Người dùng Facebook"
        },
        {
            "id": "61560118331700",
            "count": 0,
            "name": "Người dùng Facebook"
        },
        {
            "id": "61558510602126",
            "count": 0,
            "name": "Người dùng Facebook"
        },
        {
            "id": "61560069467799",
            "count": 0,
            "name": "Người dùng Facebook"
        },
        {
            "id": "61559438575046",
            "count": 0,
            "name": "Ngg Văn Hiếu"
        },
        {
            "id": "61560654511584",
            "count": 0,
            "name": "Người dùng Facebook"
        },
        {
            "id": "61560926830133",
            "count": 0,
            "name": "Chỉ　Cần　Một　Ngày　Tồi　Tệ　 Thôi　Nó　Sẽ　Biến　Một　Kẻ　 Tỉnh　Táo　Thành　Một　Kẻ Điên"
        },
        {
            "id": "61559282801359",
            "count": 0,
            "name": "Hphong　Yeu　Chip　Ở Mọi　Vũ　Trụ"
        },
        {
            "id": "61560606513186",
            "count": 0,
            "name": "Người dùng Facebook"
        },
        {
            "id": "100083847474323",
            "count": 0,
            "name": "Nguyễn Quốc Pháp"
        },
        {
            "id": "61553763794708",
            "count": 0,
            "name": "Ng Hongg Ánhh"
        },
        {
            "id": "61552084853331",
            "count": 0,
            "name": "Người dùng Facebook"
        },
        {
            "id": "61561570561761",
            "count": 0,
            "name": "Người dùng Facebook"
        },
        {
            "id": "100075784943859",
            "count": 11,
            "name": "An Huỳnh"
        },
        {
            "id": "61561504335762",
            "count": 0,
            "name": "Người dùng Facebook"
        },
        {
            "id": "61559903816343",
            "count": 0,
            "name": "Người dùng Facebook"
        },
        {
            "id": "61560450915670",
            "count": 0,
            "name": "Người dùng Facebook"
        },
        {
            "id": "61556755597888",
            "count": 0,
            "name": "Nguyễn Văn Toàn"
        },
        {
            "id": "61561947542709",
            "count": 0,
            "name": "Người dùng Facebook"
        },
        {
            "id": "100088031225325",
            "count": 0,
            "name": "Lê Văn Hoàng"
        },
        {
            "id": "61557790880926",
            "count": 0,
            "name": "Người dùng Facebook"
        },
        {
            "id": "61562151205816",
            "count": 0,
            "name": "Người dùng Facebook"
        },
        {
            "id": "61550022652935",
            "count": 0,
            "name": "Kaiotard Chuche"
        },
        {
            "id": "61561608374000",
            "count": 0,
            "name": "Uyên Hạ"
        },
        {
            "id": "61561727491080",
            "count": 0,
            "name": "Người dùng Facebook"
        },
        {
            "id": "61561995988657",
            "count": 0,
            "name": "Người dùng Facebook"
        },
        {
            "id": "100078717550219",
            "count": 0,
            "name": "Trương Trần Mie"
        },
        {
            "id": "61561985909917",
            "count": 0,
            "name": "Người dùng Facebook"
        },
        {
            "id": "61562071387946",
            "count": 0,
            "name": "Người dùng Facebook"
        },
        {
            "id": "61560368315094",
            "count": 0,
            "name": "Người dùng Facebook"
        },
        {
            "id": "100037780020873",
            "count": 0,
            "name": "Người dùng Facebook"
        },
        {
            "id": "61562086451955",
            "count": 0,
            "name": "Người dùng Facebook"
        },
        {
            "id": "61562040629561",
            "count": 0,
            "name": "Nhi Bao"
        },
        {
            "id": "61562439355061",
            "count": 0,
            "name": "️️️️️️️️️️️️️️️️️️️️️️️️️️️️️️️️️️️️️️️️️️️️️️️️️️️️️️️️️️️️️️️️️️️️️️️️️️️️️️️️️️️️️️️️️️️️️️️️️️️️️️️️️️️️️️️️️️️️️️️️️️️️️️️️️️️️️️️️️️️️️️️️️️️️️️️️️️️️️️️️️️️️️️️️️️"
        },
        {
            "id": "100003927301105",
            "count": 0,
            "name": "Người dùng Facebook"
        },
        {
            "id": "61562021202350",
            "count": 0,
            "name": "Người dùng Facebook"
        },
        {
            "id": "61562211158190",
            "count": 0,
            "name": "Người dùng Facebook"
        },
        {
            "id": "61562500093691",
            "count": 0,
            "name": "Người dùng Facebook"
        },
        {
            "id": "100091435911117",
            "count": 0,
            "name": "Ph The Hoanq"
        },
        {
            "id": "61562926262183",
            "count": 0,
            "name": "Người dùng Facebook"
        },
        {
            "id": "61560407583530",
            "count": 0,
            "name": "Người dùng Facebook"
        },
        {
            "id": "61561171259534",
            "count": 0,
            "name": "Người dùng Facebook"
        },
        {
            "id": "61562206563697",
            "count": 0,
            "name": "ᏎᏎᏎ ᏎᏎᏎ"
        },
        {
            "id": "61563454850537",
            "count": 0,
            "name": "Người dùng Facebook"
        },
        {
            "id": "61562249834774",
            "count": 0,
            "name": "Người dùng Facebook"
        },
        {
            "id": "61550536127381",
            "count": 0,
            "name": "Người dùng Facebook"
        },
        {
            "id": "100089459823872",
            "count": 0,
            "name": "Liễu Như Yên"
        },
        {
            "id": "61555016023007",
            "count": 0,
            "name": "Ngg Văn Hiếu"
        },
        {
            "id": "100093795935793",
            "count": 0,
            "name": "Người dùng Facebook"
        },
        {
            "id": "61562760102482",
            "count": 0,
            "name": "Người dùng Facebook"
        },
        {
            "id": "61561601624319",
            "count": 0,
            "name": "Người dùng Facebook"
        },
        {
            "id": "61562261835048",
            "count": 0,
            "name": "Người dùng Facebook"
        },
        {
            "id": "61562746665106",
            "count": 0,
            "name": "Người dùng Facebook"
        },
        {
            "id": "61563383187616",
            "count": 0,
            "name": "Người dùng Facebook"
        },
        {
            "id": "61563382857673",
            "count": 0,
            "name": "Người dùng Facebook"
        },
        {
            "id": "61561135898716",
            "count": 0,
            "name": "Ngồitrongtoilet Gàohéttenem"
        },
        {
            "id": "61562787787460",
            "count": 0,
            "name": "Người dùng Facebook"
        },
        {
            "id": "61560539282493",
            "count": 0,
            "name": "Người dùng Facebook"
        },
        {
            "id": "61557591564921",
            "count": 0,
            "name": "Người dùng Facebook"
        },
        {
            "id": "61554385056081",
            "count": 0,
            "name": "Người dùng Facebook"
        },
        {
            "id": "61563088362521",
            "count": 0,
            "name": "Người dùng Facebook"
        },
        {
            "id": "100001336014475",
            "count": 0,
            "name": "Người dùng Facebook"
        },
        {
            "id": "100008362837847",
            "count": 0,
            "name": "Tomi Guru"
        },
        {
            "id": "61563758873217",
            "count": 0,
            "name": "Người dùng Facebook"
        },
        {
            "id": "61559772573500",
            "count": 0,
            "name": "Người dùng Facebook"
        },
        {
            "id": "61563177670147",
            "count": 0,
            "name": "Diệp An"
        },
        {
            "id": "61553829171376",
            "count": 0,
            "name": "Người dùng Facebook"
        },
        {
            "id": "100093051642489",
            "count": 18,
            "name": "Đỗ Hải Phong"
        },
        {
            "id": "61562716052902",
            "count": 0,
            "name": "O.o T.T O.o T.T O.o T.T O.o T.T O.o T.T O.o T.T O.o T.T O.o T.T O.o T.T O.o T.T O.o T.T O.o T.T O.o T.T O.o T.T O.o T.T O.o T.T O.o T.T O.o T.T O.o T.T O.o T.T O.o T.T O.o T.T O.o T.T O.o T.T O.o T.T O.o T.T O.o T.T O.o T.T O.o T.T O.o T.T O.o T.T O.o T.T O.o T.T O.o T.T O.o T.T O.o T.T O.o T.T O.o T.T O.o T.T O.o T.T O.o T.T O.o T.T O.o T.T O.o T.T O.o T.T O.o T.T O.o T.T"
        },
        {
            "id": "61561269682645",
            "count": 0,
            "name": "Người dùng Facebook"
        },
        {
            "id": "61561331982821",
            "count": 0,
            "name": "Người dùng Facebook"
        },
        {
            "id": "100093167650888",
            "count": 0,
            "name": "𓂄𓆩𑁍𓆪𓂁 Luật Giang Hồ Anh Chơi Bằng Sub 𓃙 Dame Bay Acc Những Thằng Trap Yêu Em 𓃺 Yêu Nhau Hai Chữ Địt Nhau 𓆤 Chia Tay Bỗn Chữ Phiên Đã Hết Hạn 𓆤 Lỡ Một Ngày Em Theo Thằng Khác Anh Đau Lòng Nhưng Không Khóc Đâu Em 𓅢 Miệng Mỉm Cười Nói Em Câu Cuối Thôi Đừng Buồn Lập Nick Mới Đi Em 𓅂 𝑵𝒈𝒖𝒚𝒆𝒏 𝑻𝒓𝒂𝒏 𝑳𝒐𝒏𝒈 𝑱𝑾 𓆥 Bất Tử Theo Thời Gian𓂄𓆩𑁍𓆪𓂁"
        },
        {
            "id": "61564054794604",
            "count": 0,
            "name": "Người dùng Facebook"
        },
        {
            "id": "100001582801337",
            "count": 0,
            "name": "Người dùng Facebook"
        },
        {
            "id": "61563812093380",
            "count": 0,
            "name": "Phan Ky"
        },
        {
            "id": "100031213101487",
            "count": 0,
            "name": "Người dùng Facebook"
        },
        {
            "id": "61563455652121",
            "count": 0,
            "name": "Người dùng Facebook"
        },
        {
            "id": "61560877683960",
            "count": 10,
            "name": "Nguyễn Nhi"
        },
        {
            "id": "61551718118258",
            "count": 0,
            "name": "Nguyễn Quốc Duy"
        },
        {
            "id": "61560966655691",
            "count": 0,
            "name": "Người dùng Facebook"
        },
        {
            "id": "61563517658089",
            "count": 0,
            "name": "Bé là bot của admin KyPhan"
        },
        {
            "id": "100020460654779",
            "count": 17,
            "name": "Ky Phan"
        },
        {
            "id": "61561697074493",
            "count": 0,
            "name": "Người dùng Facebook"
        },
        {
            "id": "100091952226005",
            "count": 0,
            "name": "Na Na"
        },
        {
            "id": "61563269338729",
            "count": 0,
            "name": "Người dùng Facebook"
        },
        {
            "id": "61562955388765",
            "count": 0,
            "name": "Người dùng Facebook"
        },
        {
            "id": "61561401174728",
            "count": 0,
            "name": "Người dùng Facebook"
        },
        {
            "id": "61563783135643",
            "count": 0,
            "name": "Người dùng Facebook"
        },
        {
            "id": "100078831447837",
            "count": 0,
            "name": "Quốc Pháp"
        },
        {
            "id": "61562161232125",
            "count": 1,
            "name": "Er Golden"
        },
        {
            "id": "100000576472277",
            "count": 0,
            "name": "Người dùng Facebook"
        },
        {
            "id": "61561828030943",
            "count": 0,
            "name": "Chu Hoàng Thanh Vũ"
        },
        {
            "id": "61563212651510",
            "count": 0,
            "name": "Linda Melina"
        },
        {
            "id": "61564015621485",
            "count": 0,
            "name": "Người dùng Facebook"
        },
        {
            "id": "61563763089474",
            "count": 0,
            "name": "Người dùng Facebook"
        },
        {
            "id": "100095207345933",
            "count": 0,
            "name": "Người dùng Facebook"
        },
        {
            "id": "100000364500247",
            "count": 0,
            "name": "Người dùng Facebook"
        },
        {
            "id": "61555924809893",
            "count": 0,
            "name": "ʬʬHacker Cuteeʬʬ KHI　ANH　BUON　ANH　THUONG　LUOT　FAYBUC　NHUNG　LUC　ANH　RANH　ANH　HOC　CACH　BAN　QUI　PHAI　MOT　NGAY　DEP　TROI　TRAI　TIM　EM　BI　KHOA　ANH　UNL　ROI　NHUNG　DAP　BAY　HAI　BA　LOVE　LOVE　LOVE　LOVE　LOVE　LOVE　HACKE　BAT　TU　YEWEM　O　MOI　VUX　TRU　QUAN　MAY　CHEM　CHI　MUON　YEU　MINH　EM　THOI　I　LOOVEE　YOUU　CHIUCHIU　YEUEMMOIVUTRU　TRUM　FIFAI　YEU　EM　KHONG　PHAI - VIII"
        },
        {
            "id": "61564602716515",
            "count": 0,
            "name": "Người dùng Facebook"
        },
        {
            "id": "61563820294117",
            "count": 0,
            "name": "Người dùng Facebook"
        },
        {
            "id": "61563981387983",
            "count": 0,
            "name": "Người dùng Facebook"
        },
        {
            "id": "100001138147083",
            "count": 0,
            "name": "Người dùng Facebook"
        },
        {
            "id": "61563957028755",
            "count": 0,
            "name": "Người dùng Facebook"
        },
        {
            "id": "61563479344672",
            "count": 0,
            "name": "Người dùng Facebook"
        },
        {
            "id": "61564347531917",
            "count": 0,
            "name": "Người dùng Facebook"
        },
        {
            "id": "61563015765425",
            "count": 0,
            "name": "Này Con"
        },
        {
            "id": "61563588044195",
            "count": 0,
            "name": "Người dùng Facebook"
        },
        {
            "id": "61562946966445",
            "count": 0,
            "name": "Người dùng Facebook"
        },
        {
            "id": "61561642858727",
            "count": 0,
            "name": "Người dùng Facebook"
        },
        {
            "id": "61565176111062",
            "count": 0,
            "name": "An Huỳnh"
        },
        {
            "id": "100030236827904",
            "count": 0,
            "name": "Nguyen Hao YT"
        },
        {
            "id": "61564010925170",
            "count": 0,
            "name": "Người dùng Facebook"
        },
        {
            "id": "61565118609699",
            "count": 0,
            "name": "Người dùng Facebook"
        },
        {
            "id": "61564880897252",
            "count": 0,
            "name": "Người dùng Facebook"
        },
        {
            "id": "61565496582725",
            "count": 0,
            "name": "ʬʬHphong Dzʬʬ ANK　LA　HOT　WAR　QUIQUAI　KE　NAM　TRUM　NEN　TANG　GAME　QUIQUAI　VA　ANK　LA　MOT　HOT　TRICKER　TAI　SEVER　VIET　NAM　NAY　LU　ĐU　MOI　NHU　ĐU　TRICK　ĐOI　BEM　CHA　THI　LE　CAI　TAY　LEN　MA　DAME　CAI　WALL　ANK　BAT　TU　VI　ANK　CO　THE　RENAME　MOI　LOAI　TEN　MA　NGUOI　THUONG　KHONG　THE　ĐAT　DUOC　NGAY　ANK　CON　TREN　CAI　MXH　NAY　THI　ANK　TU　TIN　UNLOCK　ALL　MOI　LOAI　KHOA　FAYBUT - X"
        },
        {
            "id": "61553761838963",
            "count": 10,
            "name": "Lê Bảo"
        },
        {
            "id": "100022267537746",
            "count": 0,
            "name": "An Nguyen Ngoc"
        },
        {
            "id": "61566143271001",
            "count": 0,
            "name": "Lê Văn Hoàng"
        },
        {
            "id": "100086225603286",
            "count": 0,
            "name": "Ky Phan"
        },
        {
            "id": "61561175279119",
            "count": 0
        }
    ],
    "time": 1,
    "last": {
        "time": 4,
        "day": [
            {
                "id": "61559235542444",
                "count": 0
            },
            {
                "id": "100038740121428",
                "count": 0
            },
            {
                "id": "61559777633272",
                "count": 0
            },
            {
                "id": "61559996030885",
                "count": 0
            },
            {
                "id": "61560049491747",
                "count": 0
            },
            {
                "id": "61559530484938",
                "count": 0
            },
            {
                "id": "61560099980547",
                "count": 0
            },
            {
                "id": "61560404631644",
                "count": 0
            },
            {
                "id": "61560118331700",
                "count": 0
            },
            {
                "id": "61558510602126",
                "count": 0
            },
            {
                "id": "61560069467799",
                "count": 0
            },
            {
                "id": "61559438575046",
                "count": 0
            },
            {
                "id": "61560654511584",
                "count": 0
            },
            {
                "id": "61560926830133",
                "count": 0
            },
            {
                "id": "61559282801359",
                "count": 0
            },
            {
                "id": "61560606513186",
                "count": 0
            },
            {
                "id": "100083847474323",
                "count": 0
            },
            {
                "id": "61553763794708",
                "count": 0
            },
            {
                "id": "61552084853331",
                "count": 0
            },
            {
                "id": "61561570561761",
                "count": 0
            },
            {
                "id": "100075784943859",
                "count": 0
            },
            {
                "id": "61561504335762",
                "count": 0
            },
            {
                "id": "61559903816343",
                "count": 0
            },
            {
                "id": "61560450915670",
                "count": 0
            },
            {
                "id": "61556755597888",
                "count": 0
            },
            {
                "id": "61561947542709",
                "count": 0
            },
            {
                "id": "100088031225325",
                "count": 0
            },
            {
                "id": "61557790880926",
                "count": 0
            },
            {
                "id": "61562151205816",
                "count": 0
            },
            {
                "id": "61550022652935",
                "count": 0
            },
            {
                "id": "61561608374000",
                "count": 0
            },
            {
                "id": "61561727491080",
                "count": 0
            },
            {
                "id": "61561995988657",
                "count": 0
            },
            {
                "id": "100078717550219",
                "count": 0
            },
            {
                "id": "61561985909917",
                "count": 0
            },
            {
                "id": "61562071387946",
                "count": 0
            },
            {
                "id": "61560368315094",
                "count": 0
            },
            {
                "id": "100037780020873",
                "count": 0
            },
            {
                "id": "61562086451955",
                "count": 0
            },
            {
                "id": "61562040629561",
                "count": 0
            },
            {
                "id": "61562439355061",
                "count": 0
            },
            {
                "id": "100003927301105",
                "count": 0
            },
            {
                "id": "61562021202350",
                "count": 0
            },
            {
                "id": "61562211158190",
                "count": 0
            },
            {
                "id": "61562500093691",
                "count": 0
            },
            {
                "id": "100091435911117",
                "count": 0
            },
            {
                "id": "100074484685123",
                "count": 0
            },
            {
                "id": "61562926262183",
                "count": 0
            },
            {
                "id": "61560407583530",
                "count": 0
            },
            {
                "id": "61561171259534",
                "count": 0
            },
            {
                "id": "61562206563697",
                "count": 0
            },
            {
                "id": "61563454850537",
                "count": 0
            },
            {
                "id": "61562249834774",
                "count": 0
            },
            {
                "id": "61550536127381",
                "count": 0
            },
            {
                "id": "100089459823872",
                "count": 0
            },
            {
                "id": "61555016023007",
                "count": 0
            },
            {
                "id": "100093795935793",
                "count": 0
            },
            {
                "id": "61562760102482",
                "count": 0
            },
            {
                "id": "61561601624319",
                "count": 0
            },
            {
                "id": "61562261835048",
                "count": 0
            },
            {
                "id": "61562746665106",
                "count": 0
            },
            {
                "id": "61563383187616",
                "count": 0
            },
            {
                "id": "61563382857673",
                "count": 0
            },
            {
                "id": "61561135898716",
                "count": 0
            },
            {
                "id": "61562787787460",
                "count": 0
            },
            {
                "id": "61560539282493",
                "count": 0
            },
            {
                "id": "61557591564921",
                "count": 0
            },
            {
                "id": "61554385056081",
                "count": 0
            },
            {
                "id": "61563088362521",
                "count": 0
            },
            {
                "id": "100001336014475",
                "count": 0
            },
            {
                "id": "100008362837847",
                "count": 0
            },
            {
                "id": "61563758873217",
                "count": 0
            },
            {
                "id": "61559772573500",
                "count": 0
            },
            {
                "id": "61563177670147",
                "count": 0
            },
            {
                "id": "61553829171376",
                "count": 0
            },
            {
                "id": "100093051642489",
                "count": 0
            },
            {
                "id": "61562716052902",
                "count": 0
            },
            {
                "id": "61561269682645",
                "count": 0
            },
            {
                "id": "61561331982821",
                "count": 0
            },
            {
                "id": "100093167650888",
                "count": 0
            },
            {
                "id": "61564054794604",
                "count": 0
            },
            {
                "id": "100001582801337",
                "count": 0
            },
            {
                "id": "61563812093380",
                "count": 0
            },
            {
                "id": "100031213101487",
                "count": 0
            },
            {
                "id": "61563455652121",
                "count": 0
            },
            {
                "id": "61560877683960",
                "count": 0
            },
            {
                "id": "61551718118258",
                "count": 0
            },
            {
                "id": "61560966655691",
                "count": 0
            },
            {
                "id": "61563517658089",
                "count": 0
            },
            {
                "id": "100020460654779",
                "count": 0
            },
            {
                "id": "61561697074493",
                "count": 0
            },
            {
                "id": "100091952226005",
                "count": 0
            },
            {
                "id": "61563269338729",
                "count": 0
            },
            {
                "id": "61562955388765",
                "count": 0
            },
            {
                "id": "61561401174728",
                "count": 0
            },
            {
                "id": "61563783135643",
                "count": 0
            },
            {
                "id": "100078831447837",
                "count": 0
            },
            {
                "id": "61562161232125",
                "count": 0
            },
            {
                "id": "100000576472277",
                "count": 0
            },
            {
                "id": "61563015765425",
                "count": 0
            },
            {
                "id": "61561828030943",
                "count": 0
            },
            {
                "id": "61563212651510",
                "count": 0
            },
            {
                "id": "61564015621485",
                "count": 0
            },
            {
                "id": "61563763089474",
                "count": 0
            },
            {
                "id": "100095207345933",
                "count": 0
            },
            {
                "id": "100000364500247",
                "count": 0
            },
            {
                "id": "61555924809893",
                "count": 0
            },
            {
                "id": "61564602716515",
                "count": 0
            },
            {
                "id": "61563820294117",
                "count": 0
            },
            {
                "id": "61563981387983",
                "count": 0
            },
            {
                "id": "100001138147083",
                "count": 0
            },
            {
                "id": "61563957028755",
                "count": 0
            },
            {
                "id": "61563479344672",
                "count": 0
            },
            {
                "id": "61564347531917",
                "count": 0
            },
            {
                "id": "61563588044195",
                "count": 0
            },
            {
                "id": "61558669619644",
                "count": 0
            },
            {
                "id": "61562946966445",
                "count": 0
            },
            {
                "id": "61561642858727",
                "count": 0
            },
            {
                "id": "61565176111062",
                "count": 0
            },
            {
                "id": "100030236827904",
                "count": 0
            },
            {
                "id": "100081243919879",
                "count": 0
            },
            {
                "id": "61564010925170",
                "count": 0
            },
            {
                "id": "61565118609699",
                "count": 0
            },
            {
                "id": "61564880897252",
                "count": 0
            },
            {
                "id": "61565496582725",
                "count": 0
            },
            {
                "id": "61553761838963",
                "count": 0
            },
            {
                "id": "100022267537746",
                "count": 0
            },
            {
                "id": "61566143271001",
                "count": 0
            },
            {
                "id": "100086225603286",
                "count": 0
            },
            {
                "id": "61561175279119",
                "count": 0
            }
        ],
        "week": [
            {
                "id": "61559235542444",
                "count": 0
            },
            {
                "id": "100038740121428",
                "count": 0
            },
            {
                "id": "61559777633272",
                "count": 0
            },
            {
                "id": "61559996030885",
                "count": 0
            },
            {
                "id": "61560049491747",
                "count": 0
            },
            {
                "id": "61559530484938",
                "count": 0
            },
            {
                "id": "61560099980547",
                "count": 0
            },
            {
                "id": "61560404631644",
                "count": 0
            },
            {
                "id": "61560118331700",
                "count": 0
            },
            {
                "id": "61558510602126",
                "count": 0
            },
            {
                "id": "61560069467799",
                "count": 0
            },
            {
                "id": "61559438575046",
                "count": 0
            },
            {
                "id": "61560654511584",
                "count": 0
            },
            {
                "id": "61560926830133",
                "count": 0
            },
            {
                "id": "61559282801359",
                "count": 0
            },
            {
                "id": "61560606513186",
                "count": 0
            },
            {
                "id": "100083847474323",
                "count": 0
            },
            {
                "id": "61553763794708",
                "count": 0
            },
            {
                "id": "61552084853331",
                "count": 0
            },
            {
                "id": "61561570561761",
                "count": 0
            },
            {
                "id": "100075784943859",
                "count": 0
            },
            {
                "id": "61561504335762",
                "count": 0
            },
            {
                "id": "61559903816343",
                "count": 0
            },
            {
                "id": "61560450915670",
                "count": 0
            },
            {
                "id": "61556755597888",
                "count": 0
            },
            {
                "id": "61561947542709",
                "count": 0
            },
            {
                "id": "100088031225325",
                "count": 0
            },
            {
                "id": "61557790880926",
                "count": 0
            },
            {
                "id": "61562151205816",
                "count": 0
            },
            {
                "id": "61550022652935",
                "count": 0
            },
            {
                "id": "61561608374000",
                "count": 0
            },
            {
                "id": "61561727491080",
                "count": 0
            },
            {
                "id": "61561995988657",
                "count": 0
            },
            {
                "id": "100078717550219",
                "count": 0
            },
            {
                "id": "61561985909917",
                "count": 0
            },
            {
                "id": "61562071387946",
                "count": 0
            },
            {
                "id": "61560368315094",
                "count": 0
            },
            {
                "id": "100037780020873",
                "count": 0
            },
            {
                "id": "61562086451955",
                "count": 0
            },
            {
                "id": "61562040629561",
                "count": 0
            },
            {
                "id": "61562439355061",
                "count": 0
            },
            {
                "id": "100003927301105",
                "count": 0
            },
            {
                "id": "61562021202350",
                "count": 0
            },
            {
                "id": "61562211158190",
                "count": 0
            },
            {
                "id": "61562500093691",
                "count": 0
            },
            {
                "id": "100091435911117",
                "count": 0
            },
            {
                "id": "100074484685123",
                "count": 0
            },
            {
                "id": "61562926262183",
                "count": 0
            },
            {
                "id": "61560407583530",
                "count": 0
            },
            {
                "id": "61561171259534",
                "count": 0
            },
            {
                "id": "61562206563697",
                "count": 0
            },
            {
                "id": "61563454850537",
                "count": 0
            },
            {
                "id": "61562249834774",
                "count": 0
            },
            {
                "id": "61550536127381",
                "count": 0
            },
            {
                "id": "100089459823872",
                "count": 0
            },
            {
                "id": "61555016023007",
                "count": 0
            },
            {
                "id": "100093795935793",
                "count": 0
            },
            {
                "id": "61562760102482",
                "count": 0
            },
            {
                "id": "61561601624319",
                "count": 0
            },
            {
                "id": "61562261835048",
                "count": 0
            },
            {
                "id": "61562746665106",
                "count": 0
            },
            {
                "id": "61563383187616",
                "count": 0
            },
            {
                "id": "61563382857673",
                "count": 0
            },
            {
                "id": "61561135898716",
                "count": 0
            },
            {
                "id": "61562787787460",
                "count": 0
            },
            {
                "id": "61560539282493",
                "count": 0
            },
            {
                "id": "61557591564921",
                "count": 0
            },
            {
                "id": "61554385056081",
                "count": 0
            },
            {
                "id": "61563088362521",
                "count": 0
            },
            {
                "id": "100001336014475",
                "count": 0
            },
            {
                "id": "100008362837847",
                "count": 0
            },
            {
                "id": "61563758873217",
                "count": 0
            },
            {
                "id": "61559772573500",
                "count": 0
            },
            {
                "id": "61563177670147",
                "count": 0
            },
            {
                "id": "61553829171376",
                "count": 0
            },
            {
                "id": "100093051642489",
                "count": 0
            },
            {
                "id": "61562716052902",
                "count": 0
            },
            {
                "id": "61561269682645",
                "count": 0
            },
            {
                "id": "61561331982821",
                "count": 0
            },
            {
                "id": "100093167650888",
                "count": 0
            },
            {
                "id": "61564054794604",
                "count": 0
            },
            {
                "id": "100001582801337",
                "count": 0
            },
            {
                "id": "61563812093380",
                "count": 0
            },
            {
                "id": "100031213101487",
                "count": 0
            },
            {
                "id": "61563455652121",
                "count": 0
            },
            {
                "id": "61560877683960",
                "count": 0
            },
            {
                "id": "61551718118258",
                "count": 0
            },
            {
                "id": "61560966655691",
                "count": 0
            },
            {
                "id": "61563517658089",
                "count": 0
            },
            {
                "id": "100020460654779",
                "count": 0
            },
            {
                "id": "61561697074493",
                "count": 0
            },
            {
                "id": "100091952226005",
                "count": 0
            },
            {
                "id": "61563269338729",
                "count": 0
            },
            {
                "id": "61562955388765",
                "count": 0
            },
            {
                "id": "61561401174728",
                "count": 0
            },
            {
                "id": "61563783135643",
                "count": 0
            },
            {
                "id": "100078831447837",
                "count": 0
            },
            {
                "id": "61562161232125",
                "count": 0
            },
            {
                "id": "100000576472277",
                "count": 0
            },
            {
                "id": "61563015765425",
                "count": 0
            },
            {
                "id": "61561828030943",
                "count": 0
            },
            {
                "id": "61563212651510",
                "count": 0
            },
            {
                "id": "61564015621485",
                "count": 0
            },
            {
                "id": "61563763089474",
                "count": 0
            },
            {
                "id": "100095207345933",
                "count": 0
            },
            {
                "id": "100000364500247",
                "count": 0
            },
            {
                "id": "61555924809893",
                "count": 0
            },
            {
                "id": "61564602716515",
                "count": 0
            },
            {
                "id": "61563820294117",
                "count": 0
            },
            {
                "id": "61563981387983",
                "count": 0
            },
            {
                "id": "100001138147083",
                "count": 0
            },
            {
                "id": "61563957028755",
                "count": 0
            },
            {
                "id": "61563479344672",
                "count": 0
            },
            {
                "id": "61564347531917",
                "count": 0
            },
            {
                "id": "61563588044195",
                "count": 0
            },
            {
                "id": "61558669619644",
                "count": 0
            },
            {
                "id": "61562946966445",
                "count": 0
            },
            {
                "id": "61561642858727",
                "count": 0
            },
            {
                "id": "61565176111062",
                "count": 0
            },
            {
                "id": "100030236827904",
                "count": 0
            },
            {
                "id": "100081243919879",
                "count": 0
            },
            {
                "id": "61564010925170",
                "count": 0
            },
            {
                "id": "61565118609699",
                "count": 0
            },
            {
                "id": "61564880897252",
                "count": 0
            },
            {
                "id": "61565496582725",
                "count": 0
            },
            {
                "id": "61553761838963",
                "count": 0
            },
            {
                "id": "100022267537746",
                "count": 0
            },
            {
                "id": "61566143271001",
                "count": 0
            },
            {
                "id": "100086225603286",
                "count": 0
            },
            {
                "id": "61561175279119",
                "count": 0
            }
        ]
    }
}