{
    "total": [
        {
            "id": "61562369506012",
            "count": 1
        },
        {
            "id": "100082851168864",
            "count": 26
        },
        {
            "id": "100020460654779",
            "count": 20
        },
        {
            "id": "61563479344672",
            "count": 118
        },
        {
            "id": "61564519685656",
            "count": 0
        },
        {
            "id": "100087785870911",
            "count": 0
        }
    ],
    "week": [
        {
            "id": "61562369506012",
            "count": 0,
            "name": "品川实美"
        },
        {
            "id": "100082851168864",
            "count": 0,
            "name": "Anh Tuan"
        },
        {
            "id": "100020460654779",
            "count": 0,
            "name": "Ky Phan"
        },
        {
            "id": "61563479344672",
            "count": 0,
            "name": "Người dùng Facebook"
        },
        {
            "id": "61564519685656",
            "count": 0,
            "name": "Người dùng facebook"
        },
        {
            "id": "100087785870911",
            "count": 0,
            "name": "Người dùng facebook"
        }
    ],
    "day": [
        {
            "id": "61562369506012",
            "count": 0,
            "name": "品川实美"
        },
        {
            "id": "100082851168864",
            "count": 0,
            "name": "Anh Tuan"
        },
        {
            "id": "100020460654779",
            "count": 0,
            "name": "Ky Phan"
        },
        {
            "id": "61563479344672",
            "count": 0,
            "name": "Người dùng Facebook"
        },
        {
            "id": "61564519685656",
            "count": 0,
            "name": "Người dùng facebook"
        },
        {
            "id": "100087785870911",
            "count": 0,
            "name": "Người dùng facebook"
        }
    ],
    "time": 1,
    "last": {
        "time": 3,
        "day": [
            {
                "id": "61562369506012",
                "count": 0
            },
            {
                "id": "100082851168864",
                "count": 0
            },
            {
                "id": "100020460654779",
                "count": 0
            },
            {
                "id": "61563479344672",
                "count": 0
            },
            {
                "id": "61564519685656",
                "count": 0
            },
            {
                "id": "100087785870911",
                "count": 0
            }
        ],
        "week": [
            {
                "id": "61562369506012",
                "count": 0
            },
            {
                "id": "100082851168864",
                "count": 0
            },
            {
                "id": "100020460654779",
                "count": 0
            },
            {
                "id": "61563479344672",
                "count": 0
            },
            {
                "id": "61564519685656",
                "count": 0
            },
            {
                "id": "100087785870911",
                "count": 0
            }
        ]
    }
}